django_session_switcher/__init__.py
django_session_switcher/admin.py
django_session_switcher/apps.py
django_session_switcher/middleware.py
django_session_switcher/models.py
django_session_switcher/tests.py
django_session_switcher/urls.py
django_session_switcher/views.py
django_session_switcher/migrations/0001_initial.py
django_session_switcher/migrations/__init__.py
django_session_switcher/static/sessionswitcher/output.css
django_session_switcher/templates/toolbar.html
django_session_switcher-0.2.3.dist-info/METADATA
django_session_switcher-0.2.3.dist-info/WHEEL
django_session_switcher-0.2.3.dist-info/top_level.txt
django_session_switcher-0.2.3.dist-info/RECORD
